pyclickup/__init__.py
pyclickup/list.py
pyclickup/custom_fields/__init__.py
pyclickup/custom_fields/base.py
pyclickup/custom_fields/checkbox.py
pyclickup/custom_fields/currency.py
pyclickup/custom_fields/date.py
pyclickup/custom_fields/drop_down.py
pyclickup/custom_fields/email.py
pyclickup/custom_fields/formula.py
pyclickup/custom_fields/labels.py
pyclickup/custom_fields/location.py
pyclickup/custom_fields/number.py
pyclickup/custom_fields/phone.py
pyclickup/custom_fields/relation.py
pyclickup/custom_fields/short_text.py
pyclickup/custom_fields/text.py
pyclickup/custom_fields/url.py
pyclickup/services/__init__.py
pyclickup/services/base.py
pyclickup/services/cache.py
pyclickup/services/clickup.py
pyclickup/services/geolocation.py
pyclickup/utils/__init__.py
pyclickup/utils/datastructures.py
pyclickup/utils/date_format.py
pyclickup/utils/decorators.py
pyclickup/utils/types.py
pyclickup/utils/exceptions/fields.py
pyclickup/utils/exceptions/geolocation.py
pyclickup/utils/exceptions/http.py
pyclickup/utils/exceptions/lists.py
pyclickup/utils/exceptions/tasks.py
pyclickup/utils/exceptions/validators.py
pyclickup/utils/validators/__init__.py
pyclickup/utils/validators/base.py
pyclickup/utils/validators/checkbox.py
pyclickup/utils/validators/date.py
pyclickup/utils/validators/drop_down.py
pyclickup/utils/validators/email.py
pyclickup/utils/validators/labels.py
pyclickup/utils/validators/list_options.py
pyclickup/utils/validators/number.py
pyclickup/utils/validators/phone.py
pyclickup/utils/validators/relation.py
pyclickup/utils/validators/string.py
pyclickup/utils/validators/url.py
pyclickup/utils/validators/uuid.py
python_clickup-1.0.13.dist-info/LICENSE
python_clickup-1.0.13.dist-info/METADATA
python_clickup-1.0.13.dist-info/WHEEL
python_clickup-1.0.13.dist-info/top_level.txt
python_clickup-1.0.13.dist-info/RECORD
