Metadata-Version: 2.1
Name: python-clickup
Version: 1.0.13
Summary: Library that will give you the opportunity to manipulate your ClickUp data easier.
Author-email: Pavel Stashchenko <pavel.stashchenko@gmail.com>
License: MIT License        
Project-URL: Homepage, https://github.com/Stashchen/pyclickup
Classifier: Programming Language :: Python :: 3
Classifier: License :: OSI Approved :: MIT License
Classifier: Operating System :: OS Independent
Requires-Python: >=3.8
License-File: LICENSE
Requires-Dist: requests (==2.28.1)
Requires-Dist: geopy (==2.2.0)
Provides-Extra: dev
Requires-Dist: pytest (==7.1.2) ; extra == 'dev'
